odoo/addons/beesdoo_product_usability/README.rst
odoo/addons/beesdoo_product_usability/__init__.py
odoo/addons/beesdoo_product_usability/__manifest__.py
odoo/addons/beesdoo_product_usability/models/__init__.py
odoo/addons/beesdoo_product_usability/models/beesdoo_product.py
odoo/addons/beesdoo_product_usability/readme/CONTRIBUTORS.rst
odoo/addons/beesdoo_product_usability/readme/DESCRIPTION.rst
odoo/addons/beesdoo_product_usability/static/description/index.html
odoo/addons/beesdoo_product_usability/views/beesdoo_product.xml
odoo12_addon_beesdoo_product_usability-12.0.1.0.0.99.dev4.dist-info/METADATA
odoo12_addon_beesdoo_product_usability-12.0.1.0.0.99.dev4.dist-info/WHEEL
odoo12_addon_beesdoo_product_usability-12.0.1.0.0.99.dev4.dist-info/top_level.txt
odoo12_addon_beesdoo_product_usability-12.0.1.0.0.99.dev4.dist-info/RECORD
