Metadata-Version: 2.1
Name: odoo12-addon-beesdoo-product-usability
Version: 12.0.1.0.0.99.dev4
Summary: Adapt the product views.
Home-page: https://github.com/beescoop/Obeesdoo
Author: Beescoop - Cellule IT, Coop IT Easy SCRLfs
License: AGPL-3
Platform: UNKNOWN
Classifier: Programming Language :: Python
Classifier: Framework :: Odoo
Classifier: License :: OSI Approved :: GNU Affero General Public License v3
Requires-Python: >=3.5
Requires-Dist: odoo12-addon-beesdoo-product
Requires-Dist: odoo12-addon-beesdoo-purchase
Requires-Dist: odoo12-addon-beesdoo-stock-coverage
Requires-Dist: odoo (<12.1dev,>=12.0a)
